distributed_websocket/__init__.py
distributed_websocket/_auth.py
distributed_websocket/_broker.py
distributed_websocket/_connection.py
distributed_websocket/_decorators.py
distributed_websocket/_exception_handlers.py
distributed_websocket/_exceptions.py
distributed_websocket/_matching.py
distributed_websocket/_message.py
distributed_websocket/_subscriptions.py
distributed_websocket/_types.py
distributed_websocket/manager.py
distributed_websocket/proxy.py
distributed_websocket/trash.py
distributed_websocket/utils.py
venv/bin/activate_this.py
fastapi_distributed_websocket-0.2.0.dist-info/LICENSE
fastapi_distributed_websocket-0.2.0.dist-info/METADATA
fastapi_distributed_websocket-0.2.0.dist-info/WHEEL
fastapi_distributed_websocket-0.2.0.dist-info/top_level.txt
fastapi_distributed_websocket-0.2.0.dist-info/RECORD
