Metadata-Version: 2.1
Name: fastapi-distributed-websocket
Version: 0.2.0
Summary: Large scale WebSocket with FastAPI
Home-page: https://github.com/DontPanicO/fastapi-distributed-websocket
Author: Andrea Tedeschi
Author-email: Andrea Tedeschi <andrea.tedeschi@andreatedeschi.uno>
License: MIT License
Project-URL: homepage, https://github.com/DontPanicO/fastapi-distributed-websocket
Keywords: asyncio,fastapi,websocket,distributed,pubsub
Platform: POSIX
Classifier: Development Status :: 3 - Alpha
Classifier: Programming Language :: Python
Classifier: Programming Language :: Python :: 3.10
Classifier: Programming Language :: Python :: 3.11
Classifier: Programming Language :: Python :: 3 :: Only
Classifier: License :: OSI Approved :: MIT License
Classifier: Operating System :: POSIX
Classifier: Intended Audience :: Developers
Classifier: Topic :: Software Development
Classifier: Topic :: Software Development :: Libraries
Classifier: Framework :: AsyncIO
Classifier: Framework :: FastAPI
Requires-Python: >=3.10
License-File: LICENSE
Requires-Dist: redis (>=4.3.1)
Requires-Dist: fastapi (>=0.75.2)
Requires-Dist: websockets (>=10.3)
